BenFangfaxueVimscript/README.md
BenFangfaxueVimscript/__init__.py
BenFangfaxueVimscript/__main__.py
BenFangfaxueVimscript/file.epub
BenFangfaxueVimscript/index.html
BenFangfaxueVimscript/css/__init__.py
BenFangfaxueVimscript/css/annotations.css
BenFangfaxueVimscript/css/main.css
BenFangfaxueVimscript/css/normalize.css
BenFangfaxueVimscript/css/popup.css
BenFangfaxueVimscript/font/__init__.py
BenFangfaxueVimscript/font/fontello.eot
BenFangfaxueVimscript/font/fontello.svg
BenFangfaxueVimscript/font/fontello.ttf
BenFangfaxueVimscript/font/fontello.woff
BenFangfaxueVimscript/img/__init__.py
BenFangfaxueVimscript/img/annotator-glyph-sprite.png
BenFangfaxueVimscript/img/annotator-icon-sprite.png
BenFangfaxueVimscript/img/apple-touch-icon.png
BenFangfaxueVimscript/img/cancelfullscreen.png
BenFangfaxueVimscript/img/close.png
BenFangfaxueVimscript/img/fullscreen.png
BenFangfaxueVimscript/img/loader.gif
BenFangfaxueVimscript/img/menu-icon.png
BenFangfaxueVimscript/img/save.png
BenFangfaxueVimscript/img/saved.png
BenFangfaxueVimscript/img/settings-s.png
BenFangfaxueVimscript/img/settings.png
BenFangfaxueVimscript/img/star.png
BenFangfaxueVimscript/js/__init__.py
BenFangfaxueVimscript/js/epub.js
BenFangfaxueVimscript/js/epub.min.js
BenFangfaxueVimscript/js/epub.min.map
BenFangfaxueVimscript/js/hooks.min.js
BenFangfaxueVimscript/js/hooks.min.map
BenFangfaxueVimscript/js/reader.js
BenFangfaxueVimscript/js/reader.js.map
BenFangfaxueVimscript/js/reader.min.js
BenFangfaxueVimscript/js/reader.min.map
BenFangfaxueVimscript/js/hooks/__init__.py
BenFangfaxueVimscript/js/hooks/extensions/__init__.py
BenFangfaxueVimscript/js/hooks/extensions/highlight.js
BenFangfaxueVimscript/js/libs/__init__.py
BenFangfaxueVimscript/js/libs/jquery.min.js
BenFangfaxueVimscript/js/libs/localforage.min.js
BenFangfaxueVimscript/js/libs/screenfull.js
BenFangfaxueVimscript/js/libs/screenfull.min.js
BenFangfaxueVimscript/js/libs/zip.min.js
BenFangfaxueVimscript/js/plugins/__init__.py
ben_fangfaxue_vimscript-2024.3.1.0.dist-info/METADATA
ben_fangfaxue_vimscript-2024.3.1.0.dist-info/WHEEL
ben_fangfaxue_vimscript-2024.3.1.0.dist-info/entry_points.txt
ben_fangfaxue_vimscript-2024.3.1.0.dist-info/top_level.txt
ben_fangfaxue_vimscript-2024.3.1.0.dist-info/RECORD
